Metadata-Version: 1.0
Name: WifiZberry
Version: 0.0.3
Summary: Python API to control WiFi connectivity in Raspberry
Home-page: https://github.com/renansoaress/wifiZberry
Author: Renan Soares
Author-email: renansoares@live.com
License: UNKNOWN
Platform: UNKNOWN
